PyTranslo/__init__.py
PyTranslo/api.py
PyTranslo-1.1.dist-info/LICENSE
PyTranslo-1.1.dist-info/METADATA
PyTranslo-1.1.dist-info/WHEEL
PyTranslo-1.1.dist-info/top_level.txt
PyTranslo-1.1.dist-info/RECORD
