Metadata-Version: 2.1
Name: PyTranslo
Version: 1.1
Summary: Python Client Library for Translo API.
Author-email: dannkunt <dannkunt@gmail.com>
Project-URL: github, https://github.com/dannkunt/PyTranslo
Project-URL: rapidapi, https://rapidapi.com/armangokka/api/translo
Classifier: Programming Language :: Python :: 3
Classifier: License :: OSI Approved :: GNU General Public License v3 (GPLv3)
Classifier: Operating System :: OS Independent
Requires-Python: >=3.10
License-File: LICENSE
